Metadata-Version: 1.0
Name: mensolutions-distribution
Version: 1.0
Summary: Gaussian and Binomial distributions
Home-page: UNKNOWN
Author: Emmanuel Ameh
Author-email: a@b.com
License: UNKNOWN
Platform: UNKNOWN
